audiencemanager/__init__.py
audiencemanager/__version__.py
audiencemanager/audiencemanager.py
audiencemanager/config.py
audiencemanager/connector.py
audiencemanager-0.0.5.post1.dist-info/LICENSE
audiencemanager-0.0.5.post1.dist-info/METADATA
audiencemanager-0.0.5.post1.dist-info/WHEEL
audiencemanager-0.0.5.post1.dist-info/top_level.txt
audiencemanager-0.0.5.post1.dist-info/RECORD
