Metadata-Version: 2.1
Name: audiencemanager
Version: 0.0.5.post1
Summary: Adobe Audience Manager API python wrapper
Home-page: https://github.com/pitchmuc/audiencemanager
Author: Julien Piccini
Author-email: piccini.julien@gmail.com
License: GPL
Keywords: adobe,audience manager,API,python
Platform: UNKNOWN
Classifier: Intended Audience :: Developers
Classifier: License :: OSI Approved :: GNU General Public License v3 (GPLv3)
Classifier: Operating System :: OS Independent
Classifier: Programming Language :: Python
Classifier: Topic :: Scientific/Engineering :: Information Analysis
Classifier: Programming Language :: Python :: 3.6
Classifier: Programming Language :: Python :: 3.7
Classifier: Programming Language :: Python :: 3.8
Classifier: Development Status :: 4 - Beta
Requires-Python: >=3.6
License-File: LICENSE
Requires-Dist: pandas
Requires-Dist: pathlib2
Requires-Dist: pathlib
Requires-Dist: requests
Requires-Dist: PyJWT[crypto]
Requires-Dist: PyJWT
